progtc/__init__.py
progtc/cli.py
progtc/client.py
progtc/py.typed
progtc/types.py
progtc/server/__init__.py
progtc/server/api.py
progtc/server/code_execution.py
progtc/server/code_execution_manager.py
progtc/server/config.py
progtc/server/tool_call_manager.py
progtc-0.1.6.dist-info/METADATA
progtc-0.1.6.dist-info/WHEEL
progtc-0.1.6.dist-info/entry_points.txt
progtc-0.1.6.dist-info/RECORD
