Metadata-Version: 2.4
Name: progtc
Version: 0.1.6
Summary: Programmatic tool calling for your agent.
Author-email: Callum Downie <70471360+calmdown13@users.noreply.github.com>
Classifier: Programming Language :: Python :: 3.10
Classifier: Programming Language :: Python :: 3.11
Classifier: Programming Language :: Python :: 3.12
Classifier: Programming Language :: Python :: 3.13
Classifier: Programming Language :: Python :: 3.14
Requires-Python: >=3.10
Requires-Dist: httpx-sse>=0.4.3
Requires-Dist: httpx>=0.28.1
Requires-Dist: pydantic>=2.12.5
Provides-Extra: server
Requires-Dist: fastapi>=0.123.10; extra == 'server'
Requires-Dist: rich>=14.2.0; extra == 'server'
Requires-Dist: typer>=0.20.0; extra == 'server'
Requires-Dist: uvicorn[standard]>=0.38.0; extra == 'server'
